LICENSE
MANIFEST.in
README.md
requirements.txt
setup.py
fitterlog/__init__.py
fitterlog/importer.py
fitterlog/quit.py
fitterlog/start.py
fitterlog.egg-info/PKG-INFO
fitterlog.egg-info/SOURCES.txt
fitterlog.egg-info/dependency_links.txt
fitterlog.egg-info/entry_points.txt
fitterlog.egg-info/requires.txt
fitterlog.egg-info/top_level.txt
fitterlog/arg_proxy/__init__.py
fitterlog/arg_proxy/arg_proxy.py
fitterlog/arg_proxy/types.py
fitterlog/interface/__init__.py
fitterlog/interface/experiment.py
fitterlog/interface/others.py
fitterlog/interface/paint.py
fitterlog/sql_proxy/__init__.py
fitterlog/sql_proxy/base.py
fitterlog/sql_proxy/experi.py
fitterlog/sql_proxy/others.py
fitterlog/sql_proxy/utils.py
fitterlog/sql_proxy/variable.py
fitterlog_cmd/__init__.py
fitterlog_cmd/experiment_prox.py
fitterlog_cmd/cmd_start/__init__.py
fitterlog_cmd/cmd_start/utils.py
fitterlog_server_module/__init__.py
fitterlog_server_module/manage.py
fitterlog_server_module/start_server.py
fitterlog_server_module/experiment/__init__.py
fitterlog_server_module/experiment/admin.py
fitterlog_server_module/experiment/apps.py
fitterlog_server_module/experiment/tests.py
fitterlog_server_module/experiment/urls.py
fitterlog_server_module/experiment/migrations/0001_initial.py
fitterlog_server_module/experiment/migrations/0002_experimentgroup_project.py
fitterlog_server_module/experiment/migrations/0003_auto_20200426_1535.py
fitterlog_server_module/experiment/migrations/0004_experiment_start_time.py
fitterlog_server_module/experiment/migrations/0005_auto_20200428_0122.py
fitterlog_server_module/experiment/migrations/0006_auto_20200428_0141.py
fitterlog_server_module/experiment/migrations/0007_auto_20200429_1258.py
fitterlog_server_module/experiment/migrations/0008_variable_default_val.py
fitterlog_server_module/experiment/migrations/0009_auto_20200429_2147.py
fitterlog_server_module/experiment/migrations/0010_remove_variable_default_val.py
fitterlog_server_module/experiment/migrations/0011_auto_20200501_0145.py
fitterlog_server_module/experiment/migrations/0012_auto_20200504_1648.py
fitterlog_server_module/experiment/migrations/0013_experimentgroup_start_time.py
