Metadata-Version: 2.1
Name: fitterlog
Version: 0.3.8
Summary: UNKNOWN
Home-page: http://github.com/FFTYYY/fitterlog
Author: Yang Yongyi
Author-email: yongyyang17@fudan.edu.cn
License: MIT
Platform: UNKNOWN
Requires-Python: >=3.6
